{"rpath":"/p/10.ＳＳＨＭ/サンダーボーイ","files":[{"title":"001.サンダーボーイ【設定】","path":"/p/10.ＳＳＨＭ/サンダーボーイ/001.サンダーボーイ【設定】.html"},{"title":"002.サンダーボーイ【１】 サンダーボーイ処刑！","path":"/p/10.ＳＳＨＭ/サンダーボーイ/002.サンダーボーイ【１】 サンダーボーイ処刑！.html"},{"title":"003.サンダーボーイ【２】 恐怖の傀儡師","path":"/p/10.ＳＳＨＭ/サンダーボーイ/003.サンダーボーイ【２】 恐怖の傀儡師.html"},{"title":"004.サンダーボーイ【３】 地底猿人の罠","path":"/p/10.ＳＳＨＭ/サンダーボーイ/004.サンダーボーイ【３】 地底猿人の罠.html"},{"title":"005.サンダーボーイ【４】 黒い稲妻","path":"/p/10.ＳＳＨＭ/サンダーボーイ/005.サンダーボーイ【４】 黒い稲妻.html"},{"title":"006.サンダーボーイ【５】 悪夢の学芸会","path":"/p/10.ＳＳＨＭ/サンダーボーイ/006.サンダーボーイ【５】 悪夢の学芸会.html"},{"title":"007.サンダーボーイ【６－１】 新しい戦士！？［","path":"/p/10.ＳＳＨＭ/サンダーボーイ/007.サンダーボーイ【６－１】 新しい戦士！？［.html"},{"title":"008.サンダーボーイ【６－２】 新しい戦士！？［","path":"/p/10.ＳＳＨＭ/サンダーボーイ/008.サンダーボーイ【６－２】 新しい戦士！？［.html"},{"title":"009.サンダーボーイ【７】 地底猿人の逆襲","path":"/p/10.ＳＳＨＭ/サンダーボーイ/009.サンダーボーイ【７】 地底猿人の逆襲.html"},{"title":"010.サンダーボーイ【妄想ノート】","path":"/p/10.ＳＳＨＭ/サンダーボーイ/010.サンダーボーイ【妄想ノート】.html"},{"title":"011.サンダーボーイ【８】究極の信頼","path":"/p/10.ＳＳＨＭ/サンダーボーイ/011.サンダーボーイ【８】究極の信頼.html"}],"dirs":[]}