{"rpath":"/Pixiv全ヒーロー/065.キッコウ/ヒーローカフェ","files":[{"title":"001.ヒーローカフェ１","path":"/Pixiv全ヒーロー/065.キッコウ/ヒーローカフェ/001.ヒーローカフェ１.html"},{"title":"002.ヒーローカフェ２","path":"/Pixiv全ヒーロー/065.キッコウ/ヒーローカフェ/002.ヒーローカフェ２.html"},{"title":"003.ヒーローカフェ３","path":"/Pixiv全ヒーロー/065.キッコウ/ヒーローカフェ/003.ヒーローカフェ３.html"},{"title":"004.ヒーローカフェ４","path":"/Pixiv全ヒーロー/065.キッコウ/ヒーローカフェ/004.ヒーローカフェ４.html"},{"title":"005.ヒーローカフェ５","path":"/Pixiv全ヒーロー/065.キッコウ/ヒーローカフェ/005.ヒーローカフェ５.html"},{"title":"006.ヒーローカフェ６","path":"/Pixiv全ヒーロー/065.キッコウ/ヒーローカフェ/006.ヒーローカフェ６.html"},{"title":"007.ヒーローカフェ７","path":"/Pixiv全ヒーロー/065.キッコウ/ヒーローカフェ/007.ヒーローカフェ７.html"},{"title":"008.ヒーローカフェ８","path":"/Pixiv全ヒーロー/065.キッコウ/ヒーローカフェ/008.ヒーローカフェ８.html"}],"dirs":[]}