{"rpath":"/p/07.88/少年戦士ジリオン","files":[{"title":"001.少年戦士ジリオン最大の危機第１話","path":"/p/07.88/少年戦士ジリオン/001.少年戦士ジリオン最大の危機第１話.html"},{"title":"002.少年戦士ジリオン最大の危機第２話","path":"/p/07.88/少年戦士ジリオン/002.少年戦士ジリオン最大の危機第２話.html"},{"title":"003.少年戦士ジリオン最大の危機第３話","path":"/p/07.88/少年戦士ジリオン/003.少年戦士ジリオン最大の危機第３話.html"},{"title":"004.少年戦士ジリオン最大の危機第４話","path":"/p/07.88/少年戦士ジリオン/004.少年戦士ジリオン最大の危機第４話.html"},{"title":"005.少年戦士ジリオン最大の危機第５話","path":"/p/07.88/少年戦士ジリオン/005.少年戦士ジリオン最大の危機第５話.html"},{"title":"006.少年戦士ジリオン最大の危機第６話","path":"/p/07.88/少年戦士ジリオン/006.少年戦士ジリオン最大の危機第６話.html"},{"title":"007.少年戦士ジリオン最大の危機最終話","path":"/p/07.88/少年戦士ジリオン/007.少年戦士ジリオン最大の危機最終話.html"}],"dirs":[]}